[
    {"code":"af","id":"1","countryName":"Afghanistan"},
    {"code":"dz","id":"2","countryName":"Algeria"},
    {"code":"al","id":"3","countryName":"Albania"},
    {"code":"ao","id":"6","countryName":"Angola"},
    {"code":"as","id":"4","countryName":"American Samoa"},
    {"code":"ai","id":"7","countryName":"Anguilla"},
    {"code":"ad","id":"5","countryName":"Andorra"},
    {"code":"aq","id":"8","countryName":"Antarctica"},
    {"code":"aw","id":"10","countryName":"Aruba"},
    {"code":"ag","id":"9","countryName":"Antigua and Barbuda"},
    {"code":"am","id":"11","countryName":"Armenia"},
    {"code":"ar","id":"12","countryName":"Argentina"},
    {"code":"at","id":"13","countryName":"Austria"},
    {"code":"az","id":"14","countryName":"Azerbaijan"},
    {"code":"au","id":"15","countryName":"Australia"},
    {"code":"bs","id":"16","countryName":"Bahamas"},
    {"code":"bh","id":"17","countryName":"Bahrain"},
    {"code":"bd","id":"18","countryName":"Bangladesh"},
    {"code":"bb","id":"19","countryName":"Barbados"},
    {"code":"by","id":"20","countryName":"Belarus"},
    {"code":"be","id":"21","countryName":"Belgium"},
    {"code":"bj","id":"22","countryName":"Benin"},
    {"code":"bz","id":"23","countryName":"Belize"},
    {"code":"bm","id":"24","countryName":"Bermuda"},
    {"code":"bt","id":"25","countryName":"Bhutan"},
    {"code":"bo","id":"26","countryName":"Bolivia"},
    {"code":"bv","id":"27","countryName":"Bouvet Island"},
    {"code":"bw","id":"28","countryName":"Botswana"},
    {"code":"ba","id":"29","countryName":"Bosnia and Herzegovina"},
    {"code":"io","id":"31","countryName":"British Indian Ocean Territory"},
    {"code":"br","id":"30","countryName":"Brazil"},
    {"code":"bn","id":"32","countryName":"Brunei Darussalam"},
    {"code":"bg","id":"33","countryName":"Bulgaria"},
    {"code":"kh","id":"36","countryName":"Cambodia"},
    {"code":"ca","id":"38","countryName":"Canada"},
    {"code":"cm","id":"37","countryName":"Cameroon"},
    {"code":"bf","id":"35","countryName":"Burkina Faso"},
    {"code":"bi","id":"34","countryName":"Burundi"},
    {"code":"cv","id":"39","countryName":"Cape Verde"},
    {"code":"cf","id":"41","countryName":"Central African Republic"},
    {"code":"ky","id":"40","countryName":"Cayman Islands"},
    {"code":"td","id":"42","countryName":"Chad"},
    {"code":"cl","id":"43","countryName":"Chile"},
    {"code":"cc","id":"46","countryName":"Cocos (Keeling) Islands"},
    {"code":"cx","id":"45","countryName":"Christmas Island"},
    {"code":"cn","id":"44","countryName":"China"},
    {"code":"km","id":"47","countryName":"Comoros"},
    {"code":"co","id":"48","countryName":"Colombia"},
    {"code":"cg","id":"49","countryName":"Congo"},
    {"code":"ck","id":"50","countryName":"Cook Islands"},
    {"code":"ci","id":"51","countryName":"Cote D'Ivoire"},
    {"code":"cr","id":"52","countryName":"Costa Rica"},
    {"code":"hr","id":"53","countryName":"Croatia"},
    {"code":"cu","id":"54","countryName":"Cuba"},
    {"code":"cy","id":"55","countryName":"Cyprus"},
    {"code":"cz","id":"56","countryName":"Czech Republic"},
    {"code":"dm","id":"59","countryName":"Dominica"},
    {"code":"dj","id":"58","countryName":"Djibouti"},
    {"code":"dk","id":"57","countryName":"Denmark"},
    {"code":"do","id":"60","countryName":"Dominican Republic"},
    {"code":"et","id":"66","countryName":"Ethiopia"},
    {"code":"gq","id":"63","countryName":"Equatorial Guinea"},
    {"code":"eg","id":"61","countryName":"Egypt"},
    {"code":"tl","id":"62","countryName":"East Timor"},
    {"code":"fk","id":"67","countryName":"Falkland Islands (Malvinas)"},
    {"code":"er","id":"65","countryName":"Eritrea"},
    {"code":"ec","id":"64","countryName":"Ecuador"},
    {"code":"sv","id":"68","countryName":"El Salvador"},
    {"code":"ee","id":"69","countryName":"Estonia"},
    {"code":"fj","id":"70","countryName":"Fiji"},
    {"code":"fo","id":"71","countryName":"Faroe Islands"},
    {"code":"fi","id":"72","countryName":"Finland"},
    {"code":"fr","id":"73","countryName":"France, Metropolitan"},
    {"code":"pf","id":"74","countryName":"French Polynesia"},
    {"code":"tf","id":"75","countryName":"French Southern Territories"},
    {"code":"gf","id":"76","countryName":"French Guiana"},
    {"code":"ga","id":"77","countryName":"Gabon"},
    {"code":"gm","id":"78","countryName":"Gambia"},
    {"code":"ge","id":"79","countryName":"Georgia"},
    {"code":"gh","id":"80","countryName":"Ghana"},
    {"code":"de","id":"81","countryName":"Germany"},
    {"code":"gi","id":"82","countryName":"Gibraltar"},
    {"code":"gu","id":"85","countryName":"Guam"},
    {"code":"gd","id":"83","countryName":"Grenada"},
    {"code":"gp","id":"84","countryName":"Guadeloupe"},
    {"code":"gr","id":"86","countryName":"Greece"},
    {"code":"gt","id":"88","countryName":"Guatemala"},
    {"code":"gn","id":"89","countryName":"Guinea"},
    {"code":"gw","id":"90","countryName":"Guinea-Bissau"},
    {"code":"gl","id":"87","countryName":"Greenland"},
    {"code":"gy","id":"91","countryName":"Guyana"},
    {"code":"ht","id":"92","countryName":"Haiti"},
    {"code":"hk","id":"93","countryName":"Hong Kong"},
    {"code":"hn","id":"95","countryName":"Honduras"},
    {"code":"hm","id":"94","countryName":"Heard and Mc Donald Islands"},
    {"code":"hu","id":"96","countryName":"Hungary"},
    {"code":"is","id":"97","countryName":"Iceland"},
    {"code":"ie","id":"99","countryName":"Ireland"},
    {"code":"id","id":"98","countryName":"Indonesia"},
    {"code":"in","id":"100","countryName":"India"},
    {"code":"iq","id":"101","countryName":"Iraq"},
    {"code":"ir","id":"102","countryName":"Iran (Islamic Republic of)"},
    {"code":"il","id":"103","countryName":"Israel"},
    {"code":"it","id":"104","countryName":"Italy"},
    {"code":"jm","id":"105","countryName":"Jamaica"},
    {"code":"jp","id":"106","countryName":"Japan"},
    {"code":"jo","id":"107","countryName":"Jordan"},
    {"code":"kr","id":"108","countryName":"South Korea"},
    {"code":"kz","id":"109","countryName":"Kazakhstan"},
    {"code":"kp","id":"110","countryName":"North Korea"},
    {"code":"la","id":"115","countryName":"Lao People's Democratic Republic"},
    {"code":"kw","id":"113","countryName":"Kuwait"},
    {"code":"ke","id":"111","countryName":"Kenya"},
    {"code":"kg","id":"114","countryName":"Kyrgyzstan"},
    {"code":"ki","id":"112","countryName":"Kiribati"},
    {"code":"lv","id":"116","countryName":"Latvia"},
    {"code":"lb","id":"117","countryName":"Lebanon"},
    {"code":"ls","id":"118","countryName":"Lesotho"},
    {"code":"lr","id":"119","countryName":"Liberia"},
    {"code":"ly","id":"120","countryName":"Libyan Arab Jamahiriya"},
    {"code":"li","id":"122","countryName":"Liechtenstein"},
    {"code":"lt","id":"121","countryName":"Lithuania"},
    {"code":"mo","id":"123","countryName":"Macau"},
    {"code":"lu","id":"125","countryName":"Luxembourg"},
    {"code":"mk","id":"124","countryName":"FYROM"},
    {"code":"mg","id":"126","countryName":"Madagascar"},
    {"code":"mw","id":"127","countryName":"Malawi"},
    {"code":"my","id":"128","countryName":"Malaysia"},
    {"code":"mv","id":"129","countryName":"Maldives"},
    {"code":"mh","id":"130","countryName":"Marshall Islands"},
    {"code":"ml","id":"131","countryName":"Mali"},
    {"code":"mt","id":"132","countryName":"Malta"},
    {"code":"mq","id":"133","countryName":"Martinique"},
    {"code":"mr","id":"134","countryName":"Mauritania"},
    {"code":"mu","id":"136","countryName":"Mauritius"},
    {"code":"yt","id":"135","countryName":"Mayotte"},
    {"code":"mx","id":"137","countryName":"Mexico"},
    {"code":"fm","id":"138","countryName":"Micronesia, Federated States of"},
    {"code":"ms","id":"141","countryName":"Montserrat"},
    {"code":"mc","id":"139","countryName":"Monaco"},
    {"code":"mn","id":"142","countryName":"Mongolia"},
    {"code":"ma","id":"143","countryName":"Morocco"},
    {"code":"md","id":"140","countryName":"Moldova, Republic of"},
    {"code":"na","id":"146","countryName":"Namibia"},
    {"code":"mm","id":"145","countryName":"Myanmar"},
    {"code":"mz","id":"144","countryName":"Mozambique"},
    {"code":"np","id":"147","countryName":"Nepal"},
    {"code":"nr","id":"148","countryName":"Nauru"},
    {"code":"nl","id":"149","countryName":"Netherlands"},
    {"code":"an","id":"150","countryName":"Netherlands Antilles"},
    {"code":"nc","id":"151","countryName":"New Caledonia"},
    {"code":"nz","id":"152","countryName":"New Zealand"},
    {"code":"ne","id":"156","countryName":"Niger"},
    {"code":"ni","id":"153","countryName":"Nicaragua"},
    {"code":"ng","id":"154","countryName":"Nigeria"},
    {"code":"nu","id":"155","countryName":"Niue"},
    {"code":"nf","id":"157","countryName":"Norfolk Island"},
    {"code":"mp","id":"158","countryName":"Northern Mariana Islands"},
    {"code":"om","id":"159","countryName":"Oman"},
    {"code":"pw","id":"161","countryName":"Palau"},
    {"code":"pg","id":"164","countryName":"Papua New Guinea"},
    {"code":"no","id":"163","countryName":"Norway"},
    {"code":"py","id":"165","countryName":"Paraguay"},
    {"code":"pk","id":"160","countryName":"Pakistan"},
    {"code":"pa","id":"162","countryName":"Panama"},
    {"code":"pn","id":"166","countryName":"Pitcairn"},
    {"code":"ph","id":"167","countryName":"Philippines"},
    {"code":"pe","id":"169","countryName":"Peru"},
    {"code":"pt","id":"168","countryName":"Portugal"},
    {"code":"re","id":"172","countryName":"Reunion"},
    {"code":"qa","id":"173","countryName":"Qatar"},
    {"code":"pr","id":"171","countryName":"Puerto Rico"},
    {"code":"pl","id":"170","countryName":"Poland"},
    {"code":"ru","id":"174","countryName":"Russian Federation"},
    {"code":"ro","id":"175","countryName":"Romania"},
    {"code":"rw","id":"176","countryName":"Rwanda"},
    {"code":"lc","id":"177","countryName":"Saint Lucia"},
    {"code":"kn","id":"178","countryName":"Saint Kitts and Nevis"},
    {"code":"vc","id":"179","countryName":"Saint Vincent and the Grenadines"},
    {"code":"ws","id":"180","countryName":"Samoa"},
    {"code":"sm","id":"181","countryName":"San Marino"},
    {"code":"st","id":"182","countryName":"Sao Tome and Principe"},
    {"code":"sa","id":"183","countryName":"Saudi Arabia"},
    {"code":"sl","id":"184","countryName":"Sierra Leone"},
    {"code":"sc","id":"187","countryName":"Seychelles"},
    {"code":"sn","id":"186","countryName":"Senegal"},
    {"code":"sk","id":"185","countryName":"Slovak Republic"},
    {"code":"sg","id":"188","countryName":"Singapore"},
    {"code":"si","id":"189","countryName":"Slovenia"},
    {"code":"sb","id":"190","countryName":"Solomon Islands"},
    {"code":"gs","id":"191","countryName":"South Georgia &amp; South Sandwich Islands"},
    {"code":"za","id":"192","countryName":"South Africa"},
    {"code":"so","id":"193","countryName":"Somalia"},
    {"code":"es","id":"194","countryName":"Spain"},
    {"code":"lk","id":"195","countryName":"Sri Lanka"},
    {"code":"pm","id":"196","countryName":"St. Pierre and Miquelon"},
    {"code":"sd","id":"197","countryName":"Sudan"},
    {"code":"sj","id":"199","countryName":"Svalbard and Jan Mayen Islands"},
    {"code":"sh","id":"198","countryName":"St. Helena"},
    {"code":"sz","id":"201","countryName":"Swaziland"},
    {"code":"sr","id":"200","countryName":"Suriname"},
    {"code":"se","id":"202","countryName":"Sweden"},
    {"code":"ch","id":"203","countryName":"Switzerland"},
    {"code":"tw","id":"205","countryName":"Taiwan"},
    {"code":"tz","id":"207","countryName":"Tanzania, United Republic of"},
    {"code":"sy","id":"204","countryName":"Syrian Arab Republic"},
    {"code":"tj","id":"206","countryName":"Tajikistan"},
    {"code":"th","id":"209","countryName":"Thailand"},
    {"code":"tg","id":"208","countryName":"Togo"},
    {"code":"to","id":"211","countryName":"Tonga"},
    {"code":"tk","id":"210","countryName":"Tokelau"},
    {"code":"tt","id":"212","countryName":"Trinidad and Tobago"},
    {"code":"tn","id":"213","countryName":"Tunisia"},
    {"code":"tr","id":"214","countryName":"Turkey"},
    {"code":"tm","id":"215","countryName":"Turkmenistan"},
    {"code":"ua","id":"217","countryName":"Ukraine"},
    {"code":"tc","id":"216","countryName":"Turks and Caicos Islands"},
    {"code":"tv","id":"218","countryName":"Tuvalu"},
    {"code":"gb","id":"221","countryName":"United Kingdom"},
    {"code":"us","id":"222","countryName":"United States"},
    {"code":"ug","id":"219","countryName":"Uganda"},
    {"code":"ae","id":"220","countryName":"United Arab Emirates"},
    {"code":"um","id":"223","countryName":"United States Minor Outlying Islands"},
    {"code":"va","id":"225","countryName":"Vatican City State (Holy See)"},
    {"code":"uy","id":"224","countryName":"Uruguay"},
    {"code":"vu","id":"227","countryName":"Vanuatu"},
    {"code":"vn","id":"226","countryName":"Viet Nam"},
    {"code":"vg","id":"230","countryName":"Virgin Islands (British)"},
    {"code":"ve","id":"228","countryName":"Venezuela"},
    {"code":"vi","id":"231","countryName":"Virgin Islands (U.S.)"},
    {"code":"eh","id":"229","countryName":"Western Sahara"},
    {"code":"uz","id":"232","countryName":"Uzbekistan"},
    {"code":"zm","id":"233","countryName":"Zambia"},
    {"code":"cd","id":"234","countryName":"Democratic Republic of Congo"},
    {"code":"ax","id":"239","countryName":"Aaland Islands"},
    {"code":"bq","id":"238","countryName":"Bonaire, Sint Eustatius and Saba"},
    {"code":"zw","id":"237","countryName":"Zimbabwe"},
    {"code":"ye","id":"235","countryName":"Yemen"},
    {"code":"wf","id":"236","countryName":"Wallis and Futuna Islands"},
    {"code":"rs","id":"240","countryName":"Serbia"},
    {"code":"me","id":"241","countryName":"Montenegro"},
    {"code":"cw","id":"242","countryName":"Curacao"},
    {"code":"ps","id":"243","countryName":"Palestinian Territory, Occupied"},
    {"code":"bl","id":"244","countryName":"St. Barthelemy"},
    {"code":"ss","id":"245","countryName":"South Sudan"},
    {"code":"mf","id":"246","countryName":"St. Martin (French part)"},
    {"code":"ac","id":"247","countryName":"Ascension Island (British)"},
    {"code":"ta","id":"250","countryName":"Tristan da Cunha"},
    {"code":"xk","id":"249","countryName":"Kosovo, Republic of"},
    {"code":"im","id":"251","countryName":"Isle of Man"},
    {"code":"ic","id":"248","countryName":"Canary Islands"},
    {"code":"gg","id":"252","countryName":"Guernsey"},
    {"code":"je","id":"253","countryName":"Jersey"}
    ]